autofxn/__init__.py
autofxn/autofxn.py
autofxn/cli.py
autofxn/version.py
autofxn-0.0.3.dist-info/LICENSE
autofxn-0.0.3.dist-info/METADATA
autofxn-0.0.3.dist-info/WHEEL
autofxn-0.0.3.dist-info/entry_points.txt
autofxn-0.0.3.dist-info/top_level.txt
autofxn-0.0.3.dist-info/RECORD
